techinrealestate/README.md
techinrealestate/__init__.py
techinrealestate/apimaker/__init__.py
techinrealestate/apimaker/zillow/__init__.py
techinrealestate/scrapeak/__init__.py
techinrealestate/scrapeak/zillow/__init__.py
techinrealestate/scrapeak/zillow/listings.py
techinrealestate/scrapeak/zillow/property_details.py
techinrealestate-1.1.5.dist-info/licenses/LICENSE
techinrealestate-1.1.5.dist-info/METADATA
techinrealestate-1.1.5.dist-info/WHEEL
techinrealestate-1.1.5.dist-info/top_level.txt
techinrealestate-1.1.5.dist-info/RECORD
