Metadata-Version: 2.4
Name: techinrealestate
Version: 1.1.5
Summary: A comprehensive Python package for collecting and analyzing real estate market data with built-in rate limiting, data cleaning, and batch processing
Home-page: https://pypi.org/project/techinrealestate/
Author: AnalyticsAriel
Author-email: AnalyticsAriel <arielherrera@analyticsariel.com>
Maintainer-email: AnalyticsAriel <arielherrera@analyticsariel.com>
License: MIT
Project-URL: Homepage, https://pypi.org/project/techinrealestate/
Project-URL: Documentation, https://pypi.org/project/techinrealestate/
Project-URL: Bug Reports, https://github.com/analyticsariel/techinrealestate-package/issues
Project-URL: Get API Key, https://www.scrapeak.com/zillow-scraper/?ref=ariel
Keywords: real estate,market data,property data,real estate api,data collection,web scraping,property listings,real estate analysis,property details,market analysis,real estate tools,batch processing,rate limiting
Classifier: Development Status :: 4 - Beta
Classifier: Intended Audience :: Developers
Classifier: Intended Audience :: Financial and Insurance Industry
Classifier: Intended Audience :: Science/Research
Classifier: License :: OSI Approved :: MIT License
Classifier: Operating System :: OS Independent
Classifier: Programming Language :: Python :: 3
Classifier: Programming Language :: Python :: 3.7
Classifier: Programming Language :: Python :: 3.8
Classifier: Programming Language :: Python :: 3.9
Classifier: Programming Language :: Python :: 3.10
Classifier: Programming Language :: Python :: 3.11
Classifier: Programming Language :: Python :: 3.12
Classifier: Topic :: Office/Business
Classifier: Topic :: Scientific/Engineering :: Information Analysis
Classifier: Topic :: Software Development :: Libraries :: Python Modules
Requires-Python: >=3.7
License-File: LICENSE
Requires-Dist: requests>=2.25.0
Provides-Extra: dev
Requires-Dist: pytest>=6.0; extra == "dev"
Requires-Dist: pytest-cov>=2.0; extra == "dev"
Requires-Dist: black>=21.0; extra == "dev"
Requires-Dist: flake8>=3.8; extra == "dev"
Requires-Dist: mypy>=0.900; extra == "dev"
Provides-Extra: docs
Requires-Dist: sphinx>=4.0; extra == "docs"
Requires-Dist: sphinx-rtd-theme>=1.0; extra == "docs"
Dynamic: author
Dynamic: home-page
Dynamic: license-file
Dynamic: requires-python
